{
	"coc.preferences.formatOnSaveFiletypes": [
		"typescript",
		"javascript",
		"javascriptreact",
		"typescriptreact",
		"html",
		"css",
		"sass",
		"scss",
		"python",
		"graphql",
		"json"
	],
	"coc.preferences.formatOnType": true,
	"coc.preferences.formatOnTypeFiletypes": [
		"typescript",
		"javascript",
		"javascriptreact",
		"typescriptreact",
		"jsx",
		"graphql"
	],
	"coc.preferences.useQuickfixForLocations": true,
	"coc.preferences.extensionUpdateCheck": "never",
	"coc.preferences.jumpCommand": "tab drop",
	"coc.preferences.bracketEnterImprove": true,
	"coc.preferences.snippetStatusText": "SNIP",
	"coc.preferences.snippetHighlight": true,
	"codeLens.enable": true,
	"suggest.completionItemKindLabels": {
		"method": "  ",
		"function": "  ",
		"variable": "[]",
		"field": "  ",
		"typeParameter": "<>",
		"constant": "  ",
		"class": " פּ ",
		"interface": " 蘒",
		"struct": "  ",
		"event": "  ",
		"operator": "  ",
		"module": "  ",
		"property": "  ",
		"enum": " 練",
		"reference": "  ",
		"keyword": "  ",
		"file": "  ",
		"folder": " ﱮ ",
		"color": "  ",
		"unit": " 塞 ",
		"snippet": "  ",
		"text": "  ",
		"constructor": "  ",
		"value": "  ",
		"enumMember": "  "
	},
	"suggest.noselect": false,
	"suggest.snippetIndicator": "",
	"suggest.labelMaxLength": 50,
	"suggest.enablePreselect": true,
	"suggest.triggerAfterInsertEnter": true,
	"suggest.removeDuplicateItems": false,
	"diagnostic.virtualText": true,
	"diagnostic.virtualTextCurrentLineOnly": false,
	"diagnostic.checkCurrentLine": true,
	"diagnostic.autoRefresh": true,
	"diagnostic.enable": true,
	"diagnostic.messageTarget": "echo",
	"diagnostic.enableHighlightLineNumber": true,
	"diagnostic.enableSign": false,
	"tsserver.disableAutomaticTypeAcquisition": false,
	"tsserver.formatOnType": true,
	"tsserver.enableTracing": true,
	"tsserver.enableJavascript": true,
	"tsserver.enable": true,
	"tsserver.npm": "~/.nvm/versions/node/v16.16.0/bin/npm",
	"tsserver.useBatchedBufferSync": true,
	"javascript.referencesCodeLens.enable": true,
	"typescript.suggest.enabled": true,
	"typescript.validate.enable": true,
	"javascript.suggestionActions.enabled": true,
	"typescript.suggestionActions.enabled": true,
	"javascript.suggest.enabled": true,
	"javascript.validate.enable": true,
	"tsserver.log": "normal",
	"javascript.autoClosingTags": true,
	"typescript.autoClosingTags": true,
	"typescript.suggest.autoImports": true,
	"javascript.suggest.autoImports": true,
	"javascript.suggest.completeJSDocs": true,
	"typescript.suggest.completeJSDocs": true,
	"typescript.inlayHints.parameterNames.enabled": "all",
	"typescript.inlayHints.variableTypes.enabled": true,
	"typescript.inlayHints.parameterTypes.enabled": true,
	"typescript.inlayHints.functionLikeReturnTypes.enabled": true,
	"typescript.inlayHints.propertyDeclarationTypes.enabled": true,
	"javascript.inlayHints.variableTypes.enabled": true,
	"javascript.inlayHints.parameterNames.enabled": "all",
	"javascript.inlayHints.parameterTypes.enabled": true,
	"javascript.inlayHints.functionLikeReturnTypes.enabled": true,
	"javascript.inlayHints.propertyDeclarationTypes.enabled": true,
	"emmet.includeLanguages": {
		"javascript": "javascriptreact",
		"typescript": "typescriptreact"
	},
	"eslint.alwaysShowStatus": true,
	"eslint.codeAction.showDocumentation": {
		"enable": true
	},
	"eslint.run": "onType",
	"eslint.format.enable": true,
	"python.linting.pylintEnabled": true,
	"python.linting.mypyEnabled": false,
	"python.linting.enabled": true,
	"python.linting.pylintArgs": [
		"--load-plugins=pylint_django",
		"--load-plugins=pylint_django.checkers.migrations",
		"--errors-only"
	],
	"rust-analyzer.enable": true,
	"rust-analyzer.lens.enable": false,
	"rust-analyzer.rustc.source": "discover",
	"rust-analyzer.completion.callable.snippets": "fill_arguments",
	"rust-analyzer.signatureInfo.detail": "full",
	"rust-analyzer.cargo.autoreload": true,
	"rust-analyzer.diagnostics.enable": true,
	"rust-analyzer.cachePriming.enable": true,
	"rust-analyzer.inlayHints.enable": false,
	"rust-analyzer.inlayHints.typeHints.enable": false,
	"rust-analyzer.checkOnSave.allTargets": true,
	"rust-analyzer.hover.links.enable": true,
	"rust-analyzer.diagnostics.experimental.enable": true,
	"rust-analyzer.inlayHints.refreshOnInsertMode": true,
	"rust-analyzer.inlayHints.chainingHints.enable": true,
	"rust-analyzer.procMacro.enable": true,
	"rust-analyzer.procMacro.attributes.enable": true,
	"rust-analyzer.files.watcher": "client",
	"rust-analyzer.diagnostics.disabled": ["unresolved-proc-macro"],
	"htmldjango.enable": true,
	"htmldjango.completion.enable": true,
	"prettier.endOfLine": "auto",
	"prettier.quoteProps": "consistent",
	"prettier.useTabs": true,
	"prettier.singleQuote": false,
	"prettier.semi": true,
	"prettier.trailingComma": "es5",
	"prettier.jsxSingleQuote": false,
	"prettier.bracketSameLine": true,
	"prettier.enableDebugLogs": true,
	"prettier.bracketSpacing": true,
	"prettier.formatterPriority": 1,
	"languageserver": {
		"graphql": {
			"enable": false,
			"command": "graphql-lsp",
			"args": ["server", "-m", "stream"],
			"filetypes": [
				"typescript",
				"typescriptreact",
				"graphql",
				"javascript",
				"javascriptreact"
			],
			"settings": {
				"graphql-config.load.legacy": true
			}
		}
	}
}
